{
  "configurations": [
    {
      "name": "Mac",
      "includePath": [
        "${workspaceFolder}/**",
        "/usr/local/include/**",
        "~/ghq/github.com/atcoder/ac-library"
      ],
      "defines": [],
      "macFrameworkPath": [],
      "compilerPath": "/usr/local/bin/g++",
      "cStandard": "c11",
      "cppStandard": "c++17",
      "intelliSenseMode": "gcc-x64"
    },
    {
      "name": "WSL",
      "intelliSenseMode": "gcc-x64",
      "compilerPath": "/usr/bin/gcc",
      "includePath": [
        "${workspaceFolder}/**",
        "/home/remin/ghq/github.com/atcoder/ac-library"
      ],
      "defines": [],
      "cStandard": "c11",
      "cppStandard": "c++17"
    }
  ],
  "version": 4
}
